{
  "info": {
    "posts_count": 30,
    " most_active_user": " null"
  },
  "results": [
    {
      "name": "User#1",
      "age": 20,
      "posts": [
        {
          "title": "User#1 Post#1",
          "description": "User#1 some description1",
          "likes_count": 31657
        }
      ],
      "most_liked_post": {
        "title": "User#1 Post#1",
        "description": "User#1 some description1",
        "likes_count": 31657
      }
    },
    {
      "name": "User#2",
      "age": 21,
      "posts": [
        {
          "title": "User#2 Post#1",
          "description": "User#2 some description1",
          "likes_count": 56870
        }
      ],
      "most_liked_post": {
        "title": "User#2 Post#1",
        "description": "User#2 some description1",
        "likes_count": 56870
      }
    },
    {
      "name": "User#3",
      "age": 22,
      "posts": [
        {
          "title": "User#3 Post#1",
          "description": "User#3 some description1",
          "likes_count": 57421
        },
        {
          "title": "User#3 Post#2",
          "description": "User#3 some description2",
          "likes_count": 92354
        },
        {
          "title": "User#3 Post#3",
          "description": "User#3 some description3",
          "likes_count": 70249
        },
        {
          "title": "User#3 Post#4",
          "description": "User#3 some description4",
          "likes_count": 15298
        },
        {
          "title": "User#3 Post#5",
          "description": "User#3 some description5",
          "likes_count": 59043
        }
      ],
      "most_liked_post": {
        "title": "User#3 Post#2",
        "description": "User#3 some description2",
        "likes_count": 92354
      }
    },
    {
      "name": "User#4",
      "age": 23,
      "posts": [
        {
          "title": "User#4 Post#1",
          "description": "User#4 some description1",
          "likes_count": 5898
        },
        {
          "title": "User#4 Post#2",
          "description": "User#4 some description2",
          "likes_count": 6863
        }
      ],
      "most_liked_post": {
        "title": "User#4 Post#2",
        "description": "User#4 some description2",
        "likes_count": 6863
      }
    },
    {
      "name": "User#5",
      "age": 24,
      "posts": [
        {
          "title": "User#5 Post#1",
          "description": "User#5 some description1",
          "likes_count": 59890
        },
        {
          "title": "User#5 Post#2",
          "description": "User#5 some description2",
          "likes_count": 47137
        },
        {
          "title": "User#5 Post#3",
          "description": "User#5 some description3",
          "likes_count": 73837
        }
      ],
      "most_liked_post": {
        "title": "User#5 Post#3",
        "description": "User#5 some description3",
        "likes_count": 73837
      }
    },
    {
      "name": "User#6",
      "age": 25,
      "posts": [
        {
          "title": "User#6 Post#1",
          "description": "User#6 some description1",
          "likes_count": 88325
        },
        {
          "title": "User#6 Post#2",
          "description": "User#6 some description2",
          "likes_count": 78594
        },
        {
          "title": "User#6 Post#3",
          "description": "User#6 some description3",
          "likes_count": 1945
        },
        {
          "title": "User#6 Post#4",
          "description": "User#6 some description4",
          "likes_count": 67607
        },
        {
          "title": "User#6 Post#5",
          "description": "User#6 some description5",
          "likes_count": 49052
        }
      ],
      "most_liked_post": {
        "title": "User#6 Post#1",
        "description": "User#6 some description1",
        "likes_count": 88325
      }
    },
    {
      "name": "User#7",
      "age": 26,
      "posts": [
        {
          "title": "User#7 Post#1",
          "description": "User#7 some description1",
          "likes_count": 68704
        },
        {
          "title": "User#7 Post#2",
          "description": "User#7 some description2",
          "likes_count": 6416
        },
        {
          "title": "User#7 Post#3",
          "description": "User#7 some description3",
          "likes_count": 15086
        },
        {
          "title": "User#7 Post#4",
          "description": "User#7 some description4",
          "likes_count": 18702
        },
        {
          "title": "User#7 Post#5",
          "description": "User#7 some description5",
          "likes_count": 20890
        }
      ],
      "most_liked_post": {
        "title": "User#7 Post#1",
        "description": "User#7 some description1",
        "likes_count": 68704
      }
    },
    {
      "name": "User#8",
      "age": 27,
      "posts": [
        {
          "title": "User#8 Post#1",
          "description": "User#8 some description1",
          "likes_count": 1663
        },
        {
          "title": "User#8 Post#2",
          "description": "User#8 some description2",
          "likes_count": 77238
        },
        {
          "title": "User#8 Post#3",
          "description": "User#8 some description3",
          "likes_count": 12912
        },
        {
          "title": "User#8 Post#4",
          "description": "User#8 some description4",
          "likes_count": 73291
        }
      ],
      "most_liked_post": {
        "title": "User#8 Post#2",
        "description": "User#8 some description2",
        "likes_count": 77238
      }
    },
    {
      "name": "User#9",
      "age": 28,
      "posts": [
        {
          "title": "User#9 Post#1",
          "description": "User#9 some description1",
          "likes_count": 72760
        },
        {
          "title": "User#9 Post#2",
          "description": "User#9 some description2",
          "likes_count": 54462
        }
      ],
      "most_liked_post": {
        "title": "User#9 Post#1",
        "description": "User#9 some description1",
        "likes_count": 72760
      }
    },
    {
      "name": "User#10",
      "age": 29,
      "posts": [
        {
          "title": "User#10 Post#1",
          "description": "User#10 some description1",
          "likes_count": 94860
        },
        {
          "title": "User#10 Post#2",
          "description": "User#10 some description2",
          "likes_count": 31607
        }
      ],
      "most_liked_post": {
        "title": "User#10 Post#1",
        "description": "User#10 some description1",
        "likes_count": 94860
      }
    }
  ]
}